waterisyou1/__init__.py
waterisyou1/account.py
waterisyou1/base.py
waterisyou1/changes.py
waterisyou1/configuration.py
waterisyou1/discover.py
waterisyou1/find.py
waterisyou1/genres.py
waterisyou1/movies.py
waterisyou1/people.py
waterisyou1/search.py
waterisyou1/tv.py
waterisyou1-1.1.dist-info/LICENSE
waterisyou1-1.1.dist-info/METADATA
waterisyou1-1.1.dist-info/WHEEL
waterisyou1-1.1.dist-info/top_level.txt
waterisyou1-1.1.dist-info/RECORD
